BrokenEnum/__init__.py
BrokenEnum/BrokenEnum.py
broken_enum-2024.1.15.dist-info/License.md
broken_enum-2024.1.15.dist-info/METADATA
broken_enum-2024.1.15.dist-info/WHEEL
broken_enum-2024.1.15.dist-info/RECORD
