Metadata-Version: 2.1
Name: broken-enum
Version: 2024.1.15
Summary: Smarter Python Enum classes
Home-page: https://github.com/BrokenSource/BrokenEnum
License: MIT
Author: Tremeschin
Author-email: tremeschin@users.noreply.github.com
Requires-Python: >=3.10,<3.13
Classifier: License :: OSI Approved :: MIT License
Classifier: Programming Language :: Python :: 3
Classifier: Programming Language :: Python :: 3.10
Classifier: Programming Language :: Python :: 3.11
Classifier: Programming Language :: Python :: 3.12
Project-URL: Documentation, https://github.com/BrokenSource/BrokenEnum
Project-URL: Repository, https://github.com/BrokenSource/BrokenEnum
